terminal_mini_games/__init__.py
terminal_mini_games/main.py
terminal_mini_games/games/__init__.py
terminal_mini_games/games/game_2048.py
terminal_mini_games/utils/__init__.py
terminal_mini_games/utils/high_score.py
terminal_mini_games-0.1.3.dist-info/LICENSE
terminal_mini_games-0.1.3.dist-info/METADATA
terminal_mini_games-0.1.3.dist-info/WHEEL
terminal_mini_games-0.1.3.dist-info/entry_points.txt
terminal_mini_games-0.1.3.dist-info/top_level.txt
terminal_mini_games-0.1.3.dist-info/RECORD
