Metadata-Version: 2.1
Name: terminal-mini-games
Version: 0.1.3
Summary: A collection of mini-games playable in the terminal
Home-page: https://github.com/hanzili/terminal-mini-games
Author: Hanzi Li
Author-email: hanzili0217@gmail.com
Classifier: Programming Language :: Python :: 3
Classifier: License :: OSI Approved :: MIT License
Classifier: Operating System :: OS Independent
Requires-Python: >=3.7
License-File: LICENSE
Requires-Dist: colorama
